diffrp/__init__.py
diffrp/__main__.py
diffrp/version.py
diffrp/loaders/__init__.py
diffrp/loaders/_trimesh_gltf.py
diffrp/loaders/gltf_loader.py
diffrp/materials/__init__.py
diffrp/materials/base_material.py
diffrp/materials/default_material.py
diffrp/materials/gltf_material.py
diffrp/plugins/__init__.py
diffrp/plugins/mikktspace/__init__.py
diffrp/plugins/mikktspace/mikktinterface.c
diffrp/plugins/mikktspace/mikktspace.c
diffrp/plugins/mikktspace/mikktspace.h
diffrp/rendering/__init__.py
diffrp/rendering/camera.py
diffrp/rendering/denoiser.py
diffrp/rendering/interpolator.py
diffrp/rendering/mixin.py
diffrp/rendering/path_tracing.py
diffrp/rendering/surface_deferred.py
diffrp/resources/__init__.py
diffrp/resources/hdris.py
diffrp/resources/denoisers/rt_hdr_alb_nrm.pt
diffrp/resources/hdri_exrs/newport_loft.exr
diffrp/resources/luts/agx-base-contrast.pt
diffrp/scene/__init__.py
diffrp/scene/lights.py
diffrp/scene/objects.py
diffrp/scene/scene.py
diffrp/scripts/__init__.py
diffrp/scripts/main.py
diffrp/scripts/quick_render.py
diffrp/utils/__init__.py
diffrp/utils/cache.py
diffrp/utils/colors.py
diffrp/utils/composite.py
diffrp/utils/coordinates.py
diffrp/utils/exchange.py
diffrp/utils/geometry.py
diffrp/utils/light_transport.py
diffrp/utils/raycaster.py
diffrp/utils/shader_ops.py
diffrp/utils/tone_mapping.py
diffrp/viewer/__init__.py
diffrp/viewer/mpl.py
diffrp-0.2.7.dist-info/LICENSE
diffrp-0.2.7.dist-info/METADATA
diffrp-0.2.7.dist-info/WHEEL
diffrp-0.2.7.dist-info/entry_points.txt
diffrp-0.2.7.dist-info/top_level.txt
diffrp-0.2.7.dist-info/RECORD
