Metadata-Version: 2.2
Name: diffrp
Version: 0.2.7
Summary: Differentiable Render Pipelines with PyTorch.
Home-page: https://github.com/eliphatfs/diffrp
Author: flandre.info
Author-email: flandre@scarletx.cn
Classifier: Programming Language :: Python :: 3 :: Only
Classifier: License :: OSI Approved :: Apache Software License
Classifier: Operating System :: OS Independent
Requires-Python: ~=3.7
License-File: LICENSE
Requires-Dist: rich
Requires-Dist: numpy
Requires-Dist: torch
Requires-Dist: pyexr
Requires-Dist: calibur
Requires-Dist: trimesh[easy]
Requires-Dist: torch_redstone
Requires-Dist: typing_extensions
Requires-Dist: diffrp-nvdiffrast
Dynamic: author
Dynamic: author-email
Dynamic: classifier
Dynamic: description
Dynamic: description-content-type
Dynamic: home-page
Dynamic: requires-dist
Dynamic: requires-python
Dynamic: summary
